{
  "name" : "B",
  "testType" : "SINGLE",
  "input" : {
    "type" : "STANDARD",
    "fileName" : "input.txt"
  },
  "output" : {
    "type" : "STANDARD",
    "fileName" : "output.txt"
  },
  "tests" : [ {
    "input" : "3 4",
    "output" : "0.600000000000 0.800000000000",
    "index" : 0,
    "active" : true
  }, {
    "input" : "1 0",
    "output" : "1.000000000000 0.000000000000",
    "index" : 1,
    "active" : true
  }, {
    "input" : "246 402",
    "output" : "0.521964870245 0.852966983083",
    "index" : 2,
    "active" : true
  } ],
  "location" : "src/main/java/tasks",
  "vmArgs" : "-Xmx256m -Xss64m",
  "mainClass" : "Main",
  "taskClass" : "tasks.B",
  "checkerClass" : "net.egork.chelper.checkers.TokenChecker",
  "checkerParameters" : "",
  "testClasses" : [ ],
  "date" : "",
  "contestName" : "AtCoder Beginner Contest 246",
  "truncate" : true,
  "inputClass" : "java.util.Scanner",
  "outputClass" : "java.io.PrintWriter",
  "includeLocale" : false,
  "failOnOverflow" : false,
  "interactive" : false,
  "interactor" : "net.egork.chelper.tester.Interactor"
}